mcp_naver/__init__.py
mcp_naver/server.py
mcp_naver/hosts/__init__.py
mcp_naver/hosts/claude_desktop.py
mcp_naver/hosts/cursor.py
mcp_naver-0.1.5.dist-info/METADATA
mcp_naver-0.1.5.dist-info/WHEEL
mcp_naver-0.1.5.dist-info/entry_points.txt
mcp_naver-0.1.5.dist-info/licenses/LICENSE
mcp_naver-0.1.5.dist-info/RECORD
