Metadata-Version: 2.4
Name: mcp-naver
Version: 0.1.5
Summary: A Python library that provides easy access to Naver Open APIs using FastMCP, including search services for blogs, news, books, encyclopedia, cafes, Q&A, local information, images, shopping, and more
Project-URL: Repository, https://github.com/pfldy2850/py-mcp-naver.git
Project-URL: Issues, https://github.com/pfldy2850/py-mcp-naver/issues
Project-URL: Github, https://github.com/pfldy2850/py-mcp-naver
Author-email: Dongyong Lee <pfldy2850@gmail.com>
License-File: LICENSE
Requires-Python: >=3.10
Requires-Dist: fastmcp>=0.4.1
Requires-Dist: httpx>=0.28.1
Requires-Dist: pydantic>=2.10.6
Requires-Dist: xmltodict>=0.14.2
